{
  "method": "PARSEC-calibrated RGB mass grid",
  "input_teff": 5922.0,
  "input_logg": 2.93,
  "teff_err_expanded": 300.0,
  "logg_err_expanded": 0.4,
  "feh_range": [
    -0.5,
    0.3
  ],
  "age_range_gyr": [
    1.0,
    12.0
  ],
  "n_mc_samples": 49413,
  "mc_summary": {
    "median": 1.09,
    "mean": 1.2,
    "std": 0.48,
    "ci68": [
      0.77,
      1.62
    ],
    "ci90": [
      0.63,
      2.12
    ]
  },
  "adopted_vs_grid": {
    "adopted_central": 1.34,
    "adopted_sigma": 0.4,
    "grid_median": 1.09,
    "grid_sigma": 0.48,
    "consistent": true
  },
  "grid_table": [
    {
      "feh": -0.5,
      "age_gyr": 1.0,
      "M1_msun": 2.26
    },
    {
      "feh": -0.5,
      "age_gyr": 1.5,
      "M1_msun": 2.01
    },
    {
      "feh": -0.5,
      "age_gyr": 2.0,
      "M1_msun": 1.71
    },
    {
      "feh": -0.5,
      "age_gyr": 3.0,
      "M1_msun": 1.4
    },
    {
      "feh": -0.5,
      "age_gyr": 5.0,
      "M1_msun": 1.22
    },
    {
      "feh": -0.5,
      "age_gyr": 7.0,
      "M1_msun": 1.1
    },
    {
      "feh": -0.5,
      "age_gyr": 10.0,
      "M1_msun": 1.0
    },
    {
      "feh": -0.5,
      "age_gyr": 12.0,
      "M1_msun": 1.0
    },
    {
      "feh": -0.3,
      "age_gyr": 1.0,
      "M1_msun": 2.11
    },
    {
      "feh": -0.3,
      "age_gyr": 1.5,
      "M1_msun": 1.88
    },
    {
      "feh": -0.3,
      "age_gyr": 2.0,
      "M1_msun": 1.59
    },
    {
      "feh": -0.3,
      "age_gyr": 3.0,
      "M1_msun": 1.31
    },
    {
      "feh": -0.3,
      "age_gyr": 5.0,
      "M1_msun": 1.14
    },
    {
      "feh": -0.3,
      "age_gyr": 7.0,
      "M1_msun": 1.02
    },
    {
      "feh": -0.3,
      "age_gyr": 10.0,
      "M1_msun": 0.93
    },
    {
      "feh": -0.3,
      "age_gyr": 12.0,
      "M1_msun": 0.93
    },
    {
      "feh": -0.1,
      "age_gyr": 1.0,
      "M1_msun": 1.97
    },
    {
      "feh": -0.1,
      "age_gyr": 1.5,
      "M1_msun": 1.75
    },
    {
      "feh": -0.1,
      "age_gyr": 2.0,
      "M1_msun": 1.49
    },
    {
      "feh": -0.1,
      "age_gyr": 3.0,
      "M1_msun": 1.22
    },
    {
      "feh": -0.1,
      "age_gyr": 5.0,
      "M1_msun": 1.06
    },
    {
      "feh": -0.1,
      "age_gyr": 7.0,
      "M1_msun": 0.96
    },
    {
      "feh": -0.1,
      "age_gyr": 10.0,
      "M1_msun": 0.87
    },
    {
      "feh": -0.1,
      "age_gyr": 12.0,
      "M1_msun": 0.87
    },
    {
      "feh": 0.0,
      "age_gyr": 1.0,
      "M1_msun": 1.9
    },
    {
      "feh": 0.0,
      "age_gyr": 1.5,
      "M1_msun": 1.69
    },
    {
      "feh": 0.0,
      "age_gyr": 2.0,
      "M1_msun": 1.44
    },
    {
      "feh": 0.0,
      "age_gyr": 3.0,
      "M1_msun": 1.18
    },
    {
      "feh": 0.0,
      "age_gyr": 5.0,
      "M1_msun": 1.03
    },
    {
      "feh": 0.0,
      "age_gyr": 7.0,
      "M1_msun": 0.92
    },
    {
      "feh": 0.0,
      "age_gyr": 10.0,
      "M1_msun": 0.84
    },
    {
      "feh": 0.0,
      "age_gyr": 12.0,
      "M1_msun": 0.84
    },
    {
      "feh": 0.1,
      "age_gyr": 1.0,
      "M1_msun": 1.83
    },
    {
      "feh": 0.1,
      "age_gyr": 1.5,
      "M1_msun": 1.64
    },
    {
      "feh": 0.1,
      "age_gyr": 2.0,
      "M1_msun": 1.39
    },
    {
      "feh": 0.1,
      "age_gyr": 3.0,
      "M1_msun": 1.14
    },
    {
      "feh": 0.1,
      "age_gyr": 5.0,
      "M1_msun": 0.99
    },
    {
      "feh": 0.1,
      "age_gyr": 7.0,
      "M1_msun": 0.89
    },
    {
      "feh": 0.1,
      "age_gyr": 10.0,
      "M1_msun": 0.81
    },
    {
      "feh": 0.1,
      "age_gyr": 12.0,
      "M1_msun": 0.81
    },
    {
      "feh": 0.3,
      "age_gyr": 1.0,
      "M1_msun": 1.71
    },
    {
      "feh": 0.3,
      "age_gyr": 1.5,
      "M1_msun": 1.53
    },
    {
      "feh": 0.3,
      "age_gyr": 2.0,
      "M1_msun": 1.3
    },
    {
      "feh": 0.3,
      "age_gyr": 3.0,
      "M1_msun": 1.06
    },
    {
      "feh": 0.3,
      "age_gyr": 5.0,
      "M1_msun": 0.93
    },
    {
      "feh": 0.3,
      "age_gyr": 7.0,
      "M1_msun": 0.83
    },
    {
      "feh": 0.3,
      "age_gyr": 10.0,
      "M1_msun": 0.76
    },
    {
      "feh": 0.3,
      "age_gyr": 12.0,
      "M1_msun": 0.76
    }
  ]
}